<tt xmlns:tts="http://www.w3.org/ns/ttml#styling" xml:lang="" xmlns="http://www.w3.org/ns/ttml">
  <head>
    <styling>
      <style tts:textOutline="black 2px 0px" xml:id="1" tts:fontFamily="Arial, Helvetica, sans-serif" tts:color="white" tts:fontSize="0.90c" tts:padding="2px" tts:textAlign="center"/>
    </styling>
  </head>
  <body>
    <div xml:lang="en">
      <p begin="00:00:00.00" end="00:00:06.58" style="1"><![CDATA[ ]]></p>
      <p begin="00:00:06.58" end="00:00:09.23" style="1"><![CDATA[I'm Bob Bailey, a Learning Specialist with Brightcove.]]></p>
      <p begin="00:00:09.23" end="00:00:11.50" style="1"><![CDATA[In this video, you'll learn how to add captions to your]]></p>
      <p begin="00:00:11.50" end="00:00:14.79" style="1"><![CDATA[videos using Video Cloud Studio.]]></p>
      <p begin="00:00:14.79" end="00:00:17.20" style="1"><![CDATA[Closed captions can be added to your videos to provide]]></p>
      <p begin="00:00:17.20" end="00:00:19.91" style="1"><![CDATA[additional or interpretive information to individuals who]]></p>
      <p begin="00:00:19.91" end="00:00:21.89" style="1"><![CDATA[wish to access it. ]]></p>
      <p begin="00:00:21.89" end="00:00:24.51" style="1"><![CDATA[Captions are necessary so the deaf and hard of hearing can]]></p>
      <p begin="00:00:24.51" end="00:00:28.42" style="1"><![CDATA[access the audio portion of video presentations.]]></p>
      <p begin="00:00:28.42" end="00:00:30.75" style="1"><![CDATA[Brightcove supports adding captions to your videos,]]></p>
      <p begin="00:00:30.75" end="00:00:34.00" style="1"><![CDATA[either by using the Media module and Video Cloud Studio,]]></p>
      <p begin="00:00:34.00" end="00:00:37.40" style="1"><![CDATA[or by using the Smart Player API.]]></p>
      <p begin="00:00:37.40" end="00:00:40.37" style="1"><![CDATA[To add captions to a video, you first need to create a]]></p>
      <p begin="00:00:40.37" end="00:00:42.87" style="1"><![CDATA[captions file. ]]></p>
      <p begin="00:00:42.87" end="00:00:49.59" style="1"><![CDATA[Brightcove supports both DFXP and SMPTE-TT format.]]></p>
      <p begin="00:00:49.59" end="00:00:52.93" style="1"><![CDATA[To create my captions file, I uploaded one of my videos to]]></p>
      <p begin="00:00:52.93" end="00:00:55.75" style="1"><![CDATA[one of our partners, 3Play Media.]]></p>
      <p begin="00:00:55.75" end="00:00:57.53" style="1"><![CDATA[They are just one of our partners that provide]]></p>
      <p begin="00:00:57.53" end="00:01:00.89" style="1"><![CDATA[transcription and captioning services.]]></p>
      <p begin="00:01:00.89" end="00:01:03.66" style="1"><![CDATA[For a complete list of Brightcove partners, visit]]></p>
      <p begin="00:01:03.66" end="00:01:07.35" style="1"><![CDATA[brightcove.com, and click on the partners link.]]></p>
      <p begin="00:01:07.35" end="00:01:10.07" style="1"><![CDATA[Once a transcription is complete, I could download the]]></p>
      <p begin="00:01:10.07" end="00:01:16.16" style="1"><![CDATA[captions file in DFXP format from the 3Play Media website.]]></p>
      <p begin="00:01:16.16" end="00:01:20.14" style="1"><![CDATA[Next, I need to associate the captions file with my video.]]></p>
      <p begin="00:01:20.14" end="00:01:23.30" style="1"><![CDATA[To do this, I'll go into the Media module, locate the]]></p>
      <p begin="00:01:23.30" end="00:01:27.08" style="1"><![CDATA[video, and click Edit. ]]></p>
      <p begin="00:01:27.08" end="00:01:29.90" style="1"><![CDATA[Go to the Advanced tab. ]]></p>
      <p begin="00:01:29.90" end="00:01:32.82" style="1"><![CDATA[In the Closed Captioning section, you have two options]]></p>
      <p begin="00:01:32.82" end="00:01:35.58" style="1"><![CDATA[on how the captions file is handled.]]></p>
      <p begin="00:01:35.58" end="00:01:37.84" style="1"><![CDATA[You could upload captions file to Brightcove and let]]></p>
      <p begin="00:01:37.84" end="00:01:40.84" style="1"><![CDATA[Brightcove host the captions file for you, or you can]]></p>
      <p begin="00:01:40.84" end="00:01:43.67" style="1"><![CDATA[select Remote and provide the URL to where your captions]]></p>
      <p begin="00:01:43.67" end="00:01:46.08" style="1"><![CDATA[file is located. ]]></p>
      <p begin="00:01:46.08" end="00:01:49.73" style="1"><![CDATA[I'm going to select the Upload option, and then click on the]]></p>
      <p begin="00:01:49.73" end="00:01:56.99" style="1"><![CDATA[Upload button to browse, and select my caption file.]]></p>
      <p begin="00:01:56.99" end="00:01:58.06" style="1"><![CDATA[After the file is done ]]></p>
      <p begin="00:01:58.06" end="00:02:00.44" style="1"><![CDATA[processing, click Save Changes. ]]></p>
      <p begin="00:02:00.44" end="00:02:03.50" style="1"><![CDATA[ ]]></p>
      <p begin="00:02:03.50" end="00:02:05.33" style="1"><![CDATA[To see the captions, I'm going to do a]]></p>
      <p begin="00:02:05.33" end="00:02:07.83" style="1"><![CDATA[quick Publish My Video. ]]></p>
      <p begin="00:02:07.83" end="00:02:10.35" style="1"><![CDATA[I will select my video. ]]></p>
      <p begin="00:02:10.35" end="00:02:18.01" style="1"><![CDATA[I'll go to Quick Video Publish, select a player, and]]></p>
      <p begin="00:02:18.01" end="00:02:19.26" style="1"><![CDATA[then copy the URL. ]]></p>
      <p begin="00:02:19.26" end="00:02:22.44" style="1"><![CDATA[ ]]></p>
      <p begin="00:02:22.44" end="00:02:27.06" style="1"><![CDATA[Next, I'll paste the URL into my browser.]]></p>
      <p begin="00:02:27.06" end="00:02:29.75" style="1"><![CDATA[Any player that has a video with an associated captions]]></p>
      <p begin="00:02:29.75" end="00:02:34.50" style="1"><![CDATA[file will display a CC icon on the player chrome.]]></p>
      <p begin="00:02:34.50" end="00:02:36.25" style="1"><![CDATA[I can click the CC button to toggle the]]></p>
      <p begin="00:02:36.25" end="00:02:38.21" style="1"><![CDATA[captions on and off. ]]></p>
      <p begin="00:02:38.21" end="00:02:40.34" style="1"><![CDATA[That's how easy it is to add captions to your videos.]]></p>
      <p begin="00:02:40.34" end="00:02:47.60" style="1"><![CDATA[ ]]></p>
    </div>
  </body>
</tt>
